tradestream/api/__ini__.py
tradestream/api/main.py
tradestream/clock/__ini__.py
tradestream/clock/clock.py
tradestream/core/__ini__.py
tradestream/core/models.py
tradestream/dashboard/app.py
tradestream/dashboard/components/common.py
tradestream/dashboard/components/footer.py
tradestream/dashboard/components/sidebar.py
tradestream/dashboard/components/table.py
tradestream/worker/__ini__.py
tradestream/worker/api.py
tradestream/worker/config.yml
tradestream/worker/models.py
tradestream/worker/service.py
tradestream-0.5.10.dist-info/LICENSE
tradestream-0.5.10.dist-info/METADATA
tradestream-0.5.10.dist-info/WHEEL
tradestream-0.5.10.dist-info/entry_points.txt
tradestream-0.5.10.dist-info/RECORD
