Metadata-Version: 2.1
Name: tradestream
Version: 0.5.10
Summary: A Python application with a Dash frontend, services to fetch market data, and an API server.
License: Proprietary
Author: Mac Anderson
Author-email: mac@macanderson.com
Requires-Python: >=3.12.5,<4.0.0
Classifier: License :: Other/Proprietary License
Classifier: Programming Language :: Python :: 3
Requires-Dist: aiohttp (>=3.8.5,<4.0.0)
Requires-Dist: attrs (>=24.1.0,<25.0.0)
Requires-Dist: dash (>=2.17.1,<3.0.0)
Requires-Dist: gunicorn (>=23.0.0,<24.0.0)
Requires-Dist: motor (>=3.5.1,<4.0.0)
Requires-Dist: numpy (>=1.24.4,<2.0.0)
Requires-Dist: pandas (>=2.0.3,<3.0.0)
Requires-Dist: polygon-api-client (>=1.1.0,<2.0.0)
Requires-Dist: pymongo (>=4.5.0,<5.0.0)
Requires-Dist: python-dotenv-vault (>=0.6.4,<0.7.0)
Requires-Dist: pyyaml (>=6.0.1,<7.0.0)
Requires-Dist: redis (>=5.0.8,<6.0.0)
Requires-Dist: rq (>=1.16.2,<2.0.0)
Requires-Dist: ujson (>=5.9.0,<6.0.0)
